energy_base/__init__.py
energy_base/ao_services/__init__.py
energy_base/ao_services/constants.py
energy_base/ao_services/models.py
energy_base/ao_services/requests.py
energy_base/api/__init__.py
energy_base/api/base.py
energy_base/api/pagination.py
energy_base/api/permissions/__init__.py
energy_base/api/permissions/admin_user.py
energy_base/api/permissions/base/__init__.py
energy_base/api/permissions/base/roles.py
energy_base/api/permissions/electricity.py
energy_base/api/permissions/gas.py
energy_base/api/permissions/ges.py
energy_base/api/permissions/het.py
energy_base/api/permissions/hududgaz_liqufiedgas.py
energy_base/api/permissions/hududgaz_naturalgaz.py
energy_base/api/permissions/ies.py
energy_base/api/permissions/ies_file.py
energy_base/api/permissions/liquidhydrocarbons.py
energy_base/api/permissions/met.py
energy_base/api/permissions/min_energo_report.py
energy_base/api/permissions/national_dispatch_center.py
energy_base/api/permissions/neftegaz.py
energy_base/api/permissions/neftegaz_file.py
energy_base/api/permissions/neftegaz_naturalgaz.py
energy_base/api/permissions/neftegaz_oil_well.py
energy_base/api/permissions/smart_integrity.py
energy_base/api/permissions/superuser.py
energy_base/api/permissions/uz_energo_sell.py
energy_base/api/permissions/uzbekkomir.py
energy_base/api/permissions/uzgastrade.py
energy_base/api/permissions/uztransgaz.py
energy_base/api/permissions/uztransgaz_file.py
energy_base/api/routers.py
energy_base/api/serializers.py
energy_base/api/spectacular.py
energy_base/api/views.py
energy_base/authentications/__init__.py
energy_base/authentications/microservice_authentication.py
energy_base/authentications/models.py
energy_base/cron_tasks/__init__.py
energy_base/cron_tasks/apps.py
energy_base/cron_tasks/helpers.py
energy_base/cron_tasks/urls.py
energy_base/cron_tasks/utils.py
energy_base/cron_tasks/views.py
energy_base/external_api/__init__.py
energy_base/external_api/serializers/__init__.py
energy_base-2.14.0.dist-info/METADATA
energy_base-2.14.0.dist-info/WHEEL
energy_base-2.14.0.dist-info/RECORD
