Metadata-Version: 2.1
Name: energy-base
Version: 2.14.0
Summary: Energy Base Package
Author: Olimboy
Author-email: shavkatov.olimboy@mail.ru
Requires-Python: >=3.12,<4.0
Classifier: Programming Language :: Python :: 3
Classifier: Programming Language :: Python :: 3.12
Classifier: Programming Language :: Python :: 3.13
Requires-Dist: croniter (>=2.0.3,<3.0.0)
Requires-Dist: django (==4.2.9)
Requires-Dist: django-filter (>=23.5,<24.0)
Requires-Dist: django-q (>=1.3.9,<2.0.0)
Requires-Dist: djangorestframework (>=3.14.0,<4.0.0)
Requires-Dist: djangorestframework-simplejwt[crypto] (>=5.3.1,<6.0.0)
Requires-Dist: drf-spectacular[sidecar] (>=0.27.1,<0.28.0)
Requires-Dist: inflect (>=7.2.1,<8.0.0)
Requires-Dist: minio (>=7.2.3,<8.0.0)
Requires-Dist: openpyxl (>=3.1.2,<4.0.0)
Requires-Dist: requests (>=2.31.0,<3.0.0)
